Workbook
Name Clea: raw_data__[]
Name Clean: raw_data__[]
Name Clean_Data: raw_data__[]
Name Slicer_Category: #N/A
Name Slicer_Region: #N/A
Name Slicer_Segment: #N/A

Sheet Clean_Data
A1: Order ID | B1: Ship Mode | C1: Segment | D1: Country | E1: City | F1: State | G1: Region | H1: Category | I1: Sub-Category | J1: Sales | K1: Quantity | L1: Discount | M1: Profit | N1: Profit Margin
A2: ORD-100000 | B2: Second Class | C2: Corporate | D2: India | E2: Kolkata | F2: West Bengal | G2: East | H2: Furniture | I2: Tables | J2: 18250 | K2: 7 | L2: 0 | M2: 1363.6 | N2: =raw_data__[[#This Row],[Profit]]/raw_data__[[#This Row],[Sales]] -> 0.074717808
A3: ORD-100001 | B3: Same Day | C3: Home Office | D3: India | E3: Mumbai | F3: Maharashtra | G3: West | H3: Office Supplies | I3: Binders | J3: 53680 | K3: 1 | L3: 0 | M3: 6116.51 | N3: =raw_data__[[#This Row],[Profit]]/raw_data__[[#This Row],[Sales]] -> 0.11394393
A4: ORD-100002 | B4: Standard Class | C4: Corporate | D4: India | E4: Other | F4: Other | G4: Other | H4: Technology | I4: Phones | J4: 22553 | K4: 9 | L4: 20 | M4: -172.44 | N4: =raw_data__[[#This Row],[Profit]]/raw_data__[[#This Row],[Sales]] -> -0.0076459894
A5: ORD-100003 | B5: Same Day | C5: Consumer | D5: India | E5: Other | F5: Other | G5: Other | H5: Furniture | I5: Tables | J5: 47972 | K5: 5 | L5: 0 | M5: 8880.96 | N5: =raw_data__[[#This Row],[Profit]]/raw_data__[[#This Row],[Sales]] -> 0.18512799
A6: ORD-100004 | B6: First Class | C6: Home Office | D6: India | E6: Mumbai | F6: Maharashtra | G6: West | H6: Office Supplies | I6: Storage | J6: 17498 | K6: 4 | L6: 20 | M6: -612.12 | N6: =raw_data__[[#This Row],[Profit]]/raw_data__[[#This Row],[Sales]] -> -0.034982284
A7: ORD-100006 | B7: Standard Class | C7: Home Office | D7: India | E7: Kolkata | F7: West Bengal | G7: East | H7: Furniture | I7: Chairs | J7: 59787 | K7: 3 | L7: 30 | M7: -3774.7 | N7: =raw_data__[[#This Row],[Profit]]/raw_data__[[#This Row],[Sales]] -> -0.063135799
A8: ORD-100007 | B8: Same Day | C8: Other | D8: India | E8: Hyderabad | F8: Telangana | G8: South | H8: Furniture | I8: Chairs | J8: 18454 | K8: 2 | L8: 20 | M8: -1330.47 | N8: =raw_data__[[#This Row],[Profit]]/raw_data__[[#This Row],[Sales]] -> -0.072096564
A9: ORD-100008 | B9: Same Day | C9: Home Office | D9: India | E9: Chennai | F9: Tamil Nadu | G9: South | H9: Office Supplies | I9: Storage | J9: 38038 | K9: 11 | L9: 20 | M9: -5551.06 | N9: =raw_data__[[#This Row],[Profit]]/raw_data__[[#This Row],[Sales]] -> -0.14593459
A10: ORD-100009 | B10: First Class | C10: Corporate | D10: India | E10: Hyderabad | F10: Telangana | G10: South | H10: Office Supplies | I10: Binders | J10: 49242 | K10: 7 | L10: 10 | M10: -3354.51 | N10: =raw_data__[[#This Row],[Profit]]/raw_data__[[#This Row],[Sales]] -> -0.068122944
A11: ORD-100010 | B11: Standard Class | C11: Home Office | D11: India | E11: Delhi | F11: Delhi | G11: Central | H11: Technology | I11: Accessories | J11: 15991 | K11: 3 | L11: 0 | M11: 3383.27 | N11: =raw_data__[[#This Row],[Profit]]/raw_data__[[#This Row],[Sales]] -> 0.21157339
A12: ORD-100011 | B12: Standard Class | C12: Corporate | D12: India | E12: Chennai | F12: Tamil Nadu | G12: South | H12: Technology | I12: Accessories | J12: 52721 | K12: 10 | L12: 30 | M12: -4720.08 | N12: =raw_data__[[#This Row],[Profit]]/raw_data__[[#This Row],[Sales]] -> -0.08952941
A13: ORD-100012 | B13: Second Class | C13: Other | D13: India | E13: Bangalore | F13: Karnataka | G13: South | H13: Office Supplies | I13: Storage | J13: 1656 | K13: 11 | L13: 0 | M13: 121.77 | N13: =raw_data__[[#This Row],[Profit]]/raw_data__[[#This Row],[Sales]] -> 0.073532609
... A9690: ORD-109999 | B9690: Standard Class | C9690: Home Office | D9690: India | E9690: Kolkata | F9690: West Bengal | G9690: East | H9690: Furniture | I9690: Chairs | J9690: 53229 | K9690: 6 | L9690: 0 | M9690: 4463.63 | N9690: =raw_data__[[#This Row],[Profit]]/raw_data__[[#This Row],[Sales]] -> 0.083857108
H9691: Others

Sheet Dashboard
A1: SALES PERFORMANCE DASHBOARD
A2: KEY PERFORMANCE INDICATORS | F2: INSIGHTS
A3: Total Sales | B3: =SUM(Clean_Data!J:J) -> 289622057 | F3: Office Supplies is highest revenue category
A4: Total Profit | B4: =SUM(Clean_Data!M:M) -> 9397561.8 | F4: South region dominates with highest sales
A5: Total Orders | B5: =COUNTA(Clean_Data!A:A)-1 -> 9689 | F5: 30% discount causes massive losses
A6: Profit Margin | B6: =SUM(Clean_Data!M:M)/SUM(Clean_Data!J:J) -> 0.032447673 | F6: 36.6% of orders have negative profit
A7: Avg Order Value | B7: =AVERAGE(Clean_Data!J:J) -> 29891.842 | F7: Semi-Urban orders take 2x longer to deliver
F8: Corporate segment has best profit margin

Sheet Category
A1: Category | B1: Sum of Sales | C1: Sum of Profit
A2: Technology | B2: 83947249 | C2: 2559759.8
A3: Office Supplies | B3: 86057751 | C3: 2929594.4
A4: Furniture | B4: 80104524 | C4: 2572099.5
A5: Grand Total | B5: 250109524 | C5: 8061453.7

Sheet Sub-Category
A1: Sub-Category | B1: Sum of Sales | C1: Sum of Profit
A2: Tables | B2: 37021756 | C2: 1120057.2
A3: Storage | B3: 39370176 | C3: 1451591.3
A4: Phones | B4: 37595127 | C4: 987882.28
A5: Chairs | B5: 35984947 | C5: 1145337.1
A6: Binders | B6: 38689665 | C6: 1215212.8
A7: Accessories | B7: 37757032 | C7: 1265204.9
A8: Grand Total | B8: 226418703 | C8: 7185285.6

Sheet Region
A1: Region | B1: Sum of Sales | C1: Sum of Profit
A2: West | B2: 41796252 | C2: 1342369.4
A3: South | B3: 127257085 | C3: 3690943
A4: East | B4: 38848331 | C4: 1840578.6
A5: Central | B5: 42207856 | C5: 1187562.7
A6: Grand Total | B6: 250109524 | C6: 8061453.7

Sheet Discount
A1: Discount | B1: Sum of Sales | C1: Sum of Profit
A2: 30 | B2: 43527172 | C2: -6856356
A3: 20 | B3: 41166566 | C3: -2495848.9
A4: 10 | B4: 41885496 | C4: 1769280.2
A5: 5 | B5: 37513985 | C5: 3398149.1
A6: 0 | B6: 86016305 | C6: 12246229
A7: Grand Total | B7: 250109524 | C7: 8061453.7

Sheet Ship_Mode
A1: Ship Mode | B1: Count of Order ID | C1: Sum of Sales
A2: Standard Class | B2: 1900 | C2: 57619050
A3: Second Class | B3: 2021 | C3: 60282470
A4: Same Day | B4: 1920 | C4: 57490771
A5: First Class | B5: 1976 | C5: 58268718
A6: Grand Total | B6: 7817 | C6: 233661009

Sheet Segment
A1: Segment | B1: Count of Order ID | C1: Sum of Sales | D1: Sum of Profit
A2: Home Office | B2: 2761 | C2: 83053806 | D2: 2493484.2
A3: Corporate | B3: 2766 | C3: 83079864 | D3: 2640701.1
A4: Consumer | B4: 2829 | C4: 83975854 | D4: 2927268.4
A5: Grand Total | B5: 8356 | C5: 250109524 | D5: 8061453.7

Sheet Search Tool
A1: Category Search Tool | D1: Sub-Category Seach TOOL
A2: Category | B2: Furniture | D2: Sub-Category | E2: Tables
A3: SALES | B3: =SUMIF(Clean_Data!H:H,'Search Tool'!B2,Clean_Data!J:J) -> 92420189 | D3: SALES | E3: =SUMIF(Clean_Data!I:I,E2,Clean_Data!J:J) -> 42616702
A4: PROFIT | B4: =SUMIF(Clean_Data!H:H,'Search Tool'!B2,Clean_Data!M:M) -> 2881110.6 | D4: PROFIT | E4: =SUMIF(Clean_Data!I:I,E2,Clean_Data!M:M) -> 1182700.6
A6: STATE SEARCH TOOL | D6: Segment Search Tool
A7: STATE | B7: West Bengal | D7: Segment | E7: Home Office
A8: SALES | B8: =SUMIF(Clean_Data!F:F,'Search Tool'!B7,Clean_Data!J:J) -> 41985489 | D8: SALES | E8: =SUMIF(Clean_Data!C:C,'Search Tool'!E7,Clean_Data!J:J) -> 89850575
A9: PROFIT | B9: =SUMIF(Clean_Data!F:F,'Search Tool'!B7,Clean_Data!M:M) -> 1872275.2 | D9: PROFIT | E9: =SUMIF(Clean_Data!C:C,'Search Tool'!E7,Clean_Data!M:M) -> 2666632.1

Sheet State
A1: State | B1: Sum of Sales | C1: Sum of Profit
A2: West Bengal | B2: 38848331 | C2: 1840578.6
A3: Telangana | B3: 41224009 | C3: 1275442.4
A4: Tamil Nadu | B4: 42069643 | C4: 1071034.7
A5: Maharashtra | B5: 41796252 | C5: 1342369.4
A6: Karnataka | B6: 43963433 | C6: 1344465.9
A7: Delhi | B7: 42207856 | C7: 1187562.7
A8: Grand Total | B8: 250109524 | C8: 8061453.7

Sheet Category +segment
A1: Sum of Sales | B1: Segment
A2: Category | B2: Home Office | C2: Corporate | D2: Consumer | E2: Grand Total
A3: Technology | B3: 28028325 | C3: 28629936 | D3: 27288988 | E3: 83947249
A4: Office Supplies | B4: 28584907 | C4: 28253930 | D4: 29218914 | E4: 86057751
A5: Furniture | B5: 26440574 | C5: 26195998 | D5: 27467952 | E5: 80104524
A6: Grand Total | B6: 83053806 | C6: 83079864 | D6: 83975854 | E6: 250109524

Sheet Profit by region
A1: Sum of Profit | B1: Category
A2: Region | B2: Technology | C2: Office Supplies | D2: Furniture | E2: Grand Total
A3: Central | B3: 423479.62 | C3: 368496.23 | D3: 395586.81 | E3: 1187562.7
A4: East | B4: 375773.72 | C4: 770907.41 | D4: 693897.51 | E4: 1840578.6
A5: South | B5: 1182235.2 | C5: 1419212.5 | D5: 1089495.3 | E5: 3690943
A6: West | B6: 578271.32 | C6: 370978.24 | D6: 393119.88 | E6: 1342369.4
A7: Grand Total | B7: 2559759.8 | C7: 2929594.4 | D7: 2572099.5 | E7: 8061453.7
